seletrans/__init__.py
seletrans/api/__init__.py
seletrans/api/baidu.py
seletrans/api/base.py
seletrans/api/bing.py
seletrans/api/deepl.py
seletrans/api/google.py
seletrans/api/seletrans.py
seletrans/constants/__init__.py
seletrans/constants/baidu.py
seletrans/constants/bing.py
seletrans/constants/deepl.py
seletrans/constants/google.py
seletrans/util.py
seletrans-0.4.7.dist-info/LICENSE
seletrans-0.4.7.dist-info/WHEEL
seletrans-0.4.7.dist-info/METADATA
seletrans-0.4.7.dist-info/RECORD
