Metadata-Version: 2.1
Name: seletrans
Version: 0.4.7
Summary: Translate phase using selenium.
License: MIT
Author: SErAphLi
Author-email: seraphlivery@gmail.com
Requires-Python: >=3.9,<4.0
Classifier: License :: OSI Approved :: MIT License
Classifier: Operating System :: OS Independent
Classifier: Programming Language :: Python :: 3
Classifier: Programming Language :: Python :: 3.10
Classifier: Programming Language :: Python :: 3.9
Classifier: Topic :: Utilities
Requires-Dist: beautifulsoup4 (>=4.11.1,<5.0.0)
Requires-Dist: chromedriver-autoinstaller (>=0.3.1,<0.4.0)
Requires-Dist: pytest (>=7.1.2,<8.0.0)
Requires-Dist: selenium (>=4.3.0,<5.0.0)
Requires-Dist: undetected-chromedriver (>=3.1.5,<4.0.0)
Project-URL: Bug Tracker, https://github.com/Seraphli/seletrans/issues
Project-URL: Homepage, https://github.com/Seraphli/seletrans
